{"type": "Feature", "id": 12515431, "geometry": {"type": "Point", "coordinates": [-80.128899, 8.3742]}, "properties": {"woe:id": 12515431, "woe:parent_id": 160247, "woe:name": "Rio Hato Airport", "woe:placetype": 14, "woe:placetype_name": "Airport", "woe:lang": "ENG", "iso:country": "PA", "meta:provider": ["geoplanet:7.3.1", "geoplanet:7.3.2", "geoplanet:7.4.0", "geoplanet:7.4.1", "geoplanet:7.5.1", "geoplanet:7.5.2", "geoplanet:7.6.0", "geoplanet:7.8.1", "geoplanet:7.9.0", "geoplanet:7.10.0", "geoplanet:8.0.0", "woeplanet:8.0.0"], "meta:indexed": "2020-08-20T20:56:22.710943", "meta:updated": "2020-10-14T11:59:40.951411", "woe:hierarchy": {"continent": 24865672, "country": 23424924, "town": 0, "planet": 1, "county": 26793084, "suburb": 0, "state": 2346553, "region": 0, "localadmin": 26793286}, "woe:timezone_id": 28350782, "woe:hash": "d1rp8s7zm242", "woe:centroid": [-80.128899, 8.3742], "geom:latitude": 8.3742, "geom:longitude": -80.128899, "geom:hash": "d1rp8s7zm242", "woe:latitude": 8.3742, "geom:centroid": [-80.128899, 8.3742], "woe:longitude": -80.128899, "woe:repo": "woeplanet-airport-pa", "geom:area": 0.0, "woe:scale": 19}}