{"type": "Feature", "id": 12515425, "properties": {"woe:id": 12515425, "woe:parent_id": 157170, "woe:name": "Ingenio Santa Rosa Airport", "woe:placetype": 14, "woe:placetype_name": "Airport", "woe:lang": "ENG", "iso:country": "PA", "meta:provider": ["geoplanet:7.3.1", "geoplanet:7.3.2", "geoplanet:7.4.0", "geoplanet:7.4.1", "geoplanet:7.5.1", "geoplanet:7.5.2", "geoplanet:7.6.0", "geoplanet:7.8.1", "geoplanet:7.9.0", "geoplanet:7.10.0", "geoplanet:8.0.0", "woeplanet:8.0.0"], "meta:indexed": "2020-08-20T20:56:22.705578", "meta:updated": "2020-08-22T01:58:37.099070", "woe:hierarchy": {"continent": 24865672, "country": 23424924, "town": 0, "planet": 1, "county": 26793082, "suburb": 0, "state": 2346553, "region": 0, "localadmin": 26793303}, "woe:timezone_id": 28350782, "woe:hash": "d1qwss15mxty", "woe:centroid": [-80.660004, 8.1964], "geom:latitude": 8.1964, "geom:longitude": -80.660004, "geom:hash": "d1qwss15mxty", "woe:latitude": 8.1964, "geom:centroid": [-80.660004, 8.1964], "woe:longitude": -80.660004, "woe:repo": "woeplanet-airport-pa"}, "geometry": {"coordinates": [-80.660004, 8.1964], "type": "Point"}}