{"type": "Feature", "id": 12515417, "geometry": {"type": "Point", "coordinates": [-80.410004, 7.9858]}, "properties": {"woe:id": 12515417, "woe:parent_id": 26793687, "woe:name": "Chitre Airport", "woe:placetype": 14, "woe:placetype_name": "Airport", "woe:lang": "ENG", "iso:country": "PA", "meta:provider": ["geoplanet:7.3.1", "geoplanet:7.3.2", "geoplanet:7.4.0", "geoplanet:7.4.1", "geoplanet:7.5.1", "geoplanet:7.5.2", "geoplanet:7.6.0", "geoplanet:7.8.1", "geoplanet:7.9.0", "geoplanet:7.10.0", "geoplanet:8.0.0", "woeplanet:8.0.0"], "meta:indexed": "2020-08-20T20:56:22.699228", "meta:updated": "2020-10-14T11:59:40.951851", "woe:hierarchy": {"continent": 24865672, "country": 23424924, "town": 0, "planet": 1, "county": 26793104, "suburb": 0, "state": 2346556, "region": 0, "localadmin": 26793382}, "woe:timezone_id": 28350782, "woe:hash": "d1qv6jz0xj52", "woe:centroid": [-80.410004, 7.9858], "geom:latitude": 7.9858, "geom:longitude": -80.410004, "geom:hash": "d1qv6jz0xj52", "woe:latitude": 7.9858, "geom:centroid": [-80.410004, 7.9858], "woe:longitude": -80.410004, "woe:repo": "woeplanet-airport-pa", "geom:area": 0.0, "woe:scale": 19}}